django_slack_integration-1.0.dist-info/DESCRIPTION.rst
django_slack_integration-1.0.dist-info/LICENSE.txt
django_slack_integration-1.0.dist-info/METADATA
django_slack_integration-1.0.dist-info/metadata.json
django_slack_integration-1.0.dist-info/RECORD
django_slack_integration-1.0.dist-info/top_level.txt
django_slack_integration-1.0.dist-info/WHEEL
django_slack_oauth/__init__.py
django_slack_oauth/admin.py
django_slack_oauth/models.py
django_slack_oauth/pipelines.py
django_slack_oauth/urls.py
django_slack_oauth/views.py
django_slack_oauth/migrations/0001_initial.py
django_slack_oauth/migrations/0002_slackuser_extras.py
django_slack_oauth/migrations/0003_slackuser_accesstoken_length.py
django_slack_oauth/migrations/0004_auto_20161226_1937.py
django_slack_oauth/migrations/__init__.py
